tasks.py
pelican/plugins/injector/__init__.py
pelican/plugins/injector/injector.py
pelican_injector-1.0.0.dist-info/METADATA
pelican_injector-1.0.0.dist-info/WHEEL
pelican_injector-1.0.0.dist-info/licenses/LICENSE
pelican_injector-1.0.0.dist-info/RECORD
