Metadata-Version: 2.1
Name: pelican-injector
Version: 1.0.0
Summary: Pelican plugin to inject custom code before or after specific HTML tags
Project-URL: Homepage, https://github.com/pelican-plugins/injector
Project-URL: Funding, https://donate.getpelican.com/
Project-URL: Issue Tracker, https://github.com/pelican-plugins/injector/issues
Author-email: Arturo 'Buanzo' Busleiman <buanzo@buanzo.com.ar>, Justin Mayer <entroP@gmail.com>
License: MIT
License-File: LICENSE
Classifier: Development Status :: 5 - Production/Stable
Classifier: Environment :: Console
Classifier: Framework :: Pelican
Classifier: Framework :: Pelican :: Plugins
Classifier: Intended Audience :: End Users/Desktop
Classifier: License :: OSI Approved :: MIT License
Classifier: Operating System :: OS Independent
Classifier: Programming Language :: Python :: 3
Classifier: Programming Language :: Python :: 3.8
Classifier: Programming Language :: Python :: 3.9
Classifier: Programming Language :: Python :: 3.10
Classifier: Programming Language :: Python :: 3.11
Classifier: Topic :: Internet :: WWW/HTTP
Classifier: Topic :: Software Development :: Libraries :: Python Modules
Requires-Python: >=3.8.1
Requires-Dist: beautifulsoup4>=4.12.2
Requires-Dist: pelican>=4.8.0
